cvat_sdk/__init__.py
cvat_sdk/attributes.py
cvat_sdk/exceptions.py
cvat_sdk/masks.py
cvat_sdk/models.py
cvat_sdk/version.py
cvat_sdk/api_client/__init__.py
cvat_sdk/api_client/api_client.py
cvat_sdk/api_client/configuration.py
cvat_sdk/api_client/exceptions.py
cvat_sdk/api_client/model_utils.py
cvat_sdk/api_client/rest.py
cvat_sdk/api_client/api/__init__.py
cvat_sdk/api_client/api/assets_api.py
cvat_sdk/api_client/api/auth_api.py
cvat_sdk/api_client/api/cloudstorages_api.py
cvat_sdk/api_client/api/comments_api.py
cvat_sdk/api_client/api/consensus_api.py
cvat_sdk/api_client/api/events_api.py
cvat_sdk/api_client/api/guides_api.py
cvat_sdk/api_client/api/invitations_api.py
cvat_sdk/api_client/api/issues_api.py
cvat_sdk/api_client/api/jobs_api.py
cvat_sdk/api_client/api/labels_api.py
cvat_sdk/api_client/api/lambda_api.py
cvat_sdk/api_client/api/memberships_api.py
cvat_sdk/api_client/api/organizations_api.py
cvat_sdk/api_client/api/projects_api.py
cvat_sdk/api_client/api/quality_api.py
cvat_sdk/api_client/api/requests_api.py
cvat_sdk/api_client/api/schema_api.py
cvat_sdk/api_client/api/server_api.py
cvat_sdk/api_client/api/tasks_api.py
cvat_sdk/api_client/api/users_api.py
cvat_sdk/api_client/api/webhooks_api.py
cvat_sdk/api_client/apis/__init__.py
cvat_sdk/api_client/model/__init__.py
cvat_sdk/api_client/model/about.py
cvat_sdk/api_client/model/accept_invitation_read.py
cvat_sdk/api_client/model/access_token_read.py
cvat_sdk/api_client/model/access_token_write_request.py
cvat_sdk/api_client/model/annotation_conflict.py
cvat_sdk/api_client/model/annotation_conflict_annotation_type.py
cvat_sdk/api_client/model/annotation_conflict_severity.py
cvat_sdk/api_client/model/annotation_conflict_type.py
cvat_sdk/api_client/model/annotation_file_request.py
cvat_sdk/api_client/model/annotation_guide_read.py
cvat_sdk/api_client/model/annotation_guide_write_request.py
cvat_sdk/api_client/model/annotation_id.py
cvat_sdk/api_client/model/annotation_id_shape_type.py
cvat_sdk-2.55.0.dist-info/METADATA
cvat_sdk-2.55.0.dist-info/WHEEL
cvat_sdk-2.55.0.dist-info/top_level.txt
cvat_sdk-2.55.0.dist-info/RECORD
